llama_index/readers/smart_pdf_loader/__init__.py
llama_index/readers/smart_pdf_loader/base.py
llama_index_readers_smart_pdf_loader-0.4.1.dist-info/METADATA
llama_index_readers_smart_pdf_loader-0.4.1.dist-info/WHEEL
llama_index_readers_smart_pdf_loader-0.4.1.dist-info/licenses/LICENSE
llama_index_readers_smart_pdf_loader-0.4.1.dist-info/RECORD
