Metadata-Version: 2.4
Name: llama-index-readers-smart-pdf-loader
Version: 0.4.1
Summary: llama-index readers smart_pdf_loader integration
Author-email: Your Name <you@example.com>
Maintainer: ansukla
License-Expression: MIT
License-File: LICENSE
Keywords: pdf,pdf layout,pdf table
Requires-Python: <4.0,>=3.9
Requires-Dist: llama-index-core<0.15,>=0.13.0
Requires-Dist: llmsherpa<0.2,>=0.1.4
